pydigilent/__init__.py
pydigilent/dwf.py
pydigilent/dwfconstants.py
pydigilent-0.0.4.dist-info/LICENSE
pydigilent-0.0.4.dist-info/METADATA
pydigilent-0.0.4.dist-info/WHEEL
pydigilent-0.0.4.dist-info/top_level.txt
pydigilent-0.0.4.dist-info/RECORD
