Metadata-Version: 2.1
Name: pydigilent
Version: 0.0.4
Summary: An object-oriented library for digilent hardware written in python 3
Home-page: https://github.com/jamesadevine/pydigilent
Author: James Devine
License: UNKNOWN
Project-URL: Bug Tracker, https://github.com/jamesadevine/pydigilent/issues
Platform: UNKNOWN
Classifier: Programming Language :: Python :: 3
Classifier: License :: OSI Approved :: MIT License
Classifier: Operating System :: OS Independent
Requires-Python: >=3.6
License-File: LICENSE
